arithmetic_lib/__init__.py
arithmetic_lib/arithmetic.py
arithmetic_lib-1.0.dist-info/METADATA
arithmetic_lib-1.0.dist-info/WHEEL
arithmetic_lib-1.0.dist-info/top_level.txt
arithmetic_lib-1.0.dist-info/RECORD
