Metadata-Version: 2.1
Name: arithmetic_lib
Version: 1.0
Summary: A simple arithmetic operations library
Author: Your Name
Author-email: your_email@example.com
